fretbursts-0.8.3.dist-info/WHEEL
fretbursts-0.8.3.dist-info/LICENSE.txt
fretbursts-0.8.3.dist-info/top_level.txt
fretbursts-0.8.3.dist-info/RECORD
fretbursts-0.8.3.dist-info/METADATA
fretbursts/fret_fit.py
fretbursts/burstlib_ext.py
fretbursts/__init__.py
fretbursts/burst_plot.py
fretbursts/bg_cache.py
fretbursts/gui_selection.py
fretbursts/mfit.py
fretbursts/burstsearch_c.cpython-312-x86_64-linux-musl.so
fretbursts/ph_sel.py
fretbursts/scroll_gui.py
fretbursts/burst_plot_attic.py
fretbursts/poisson_threshold.py
fretbursts/style.py
fretbursts/burstlib.py
fretbursts/background.py
fretbursts/loader_legacy.py
fretbursts/phrates_c.cpython-312-x86_64-linux-musl.so
fretbursts/hdf5.py
fretbursts/legacy_mode.py
fretbursts/loader.py
fretbursts/exptools.py
fretbursts/select_bursts.py
fretbursts/fretmath.py
fretbursts/phtools/__init__.py
fretbursts/phtools/phrates_numba.py
fretbursts/phtools/phrates_cy.pyx
fretbursts/phtools/phrates_cy.c
fretbursts/phtools/burstsearch_c.c
fretbursts/phtools/phrates.py
fretbursts/phtools/README.txt
fretbursts/phtools/burstsearch.py
fretbursts/phtools/burstsearch_c.pyx
fretbursts/utils/__init__.py
fretbursts/utils/gui.py
fretbursts/utils/misc.py
fretbursts/dataload/__init__.py
fretbursts/dataload/pytables_array_list.py
fretbursts/dataload/manta_reader.py
fretbursts/dataload/sm file structure.txt
fretbursts/dataload/spcreader.py
fretbursts/dataload/multi_ch_reader.py
fretbursts/fit/__init__.py
fretbursts/fit/compare_gaussian_fit.py
fretbursts/fit/exp_gauss_fitting.py
fretbursts/fit/fitting.py
fretbursts/fit/exp_fitting.py
fretbursts/fit/compare_gaussian_fit2.py
fretbursts/fit/weighted_kde.py
fretbursts/fit/gaussian_fitting.py
