Metadata-Version: 2.1
Name: fretbursts
Version: 0.8.3
Summary: Burst analysis toolkit for single and multi-spot smFRET data.
Author-email: Antonio Ingargiola <tritemio@gmail.com>, Paul David Harris <harripd@gmail.com>
License: GNU GENERAL PUBLIC LICENSE
Project-URL: Homepage, http://opensmfs.github.io/FRETBursts/
Project-URL: Documentation, https://fretbursts.readthedocs.io/en/latest/
Project-URL: Issues, https://github.com/OpenSMFS/FRETBursts/
Project-URL: Repository, https://github.com/OpenSMFS/FRETBursts/issues
Keywords: single-molecule FRET,smFRET,burst-analysis,biophysics
Classifier: Intended Audience :: Science/Research
Classifier: Operating System :: OS Independent
Classifier: Programming Language :: Python :: 3.7
Classifier: Programming Language :: Python :: 3.8
Classifier: Programming Language :: Python :: 3.9
Classifier: Programming Language :: Python :: 3.10
Classifier: Programming Language :: Python :: 3.11
Classifier: Topic :: Scientific/Engineering
Requires-Python: >=3.7
License-File: LICENSE.txt
Requires-Dist: numpy >=1.19
Requires-Dist: scipy >=1.2
Requires-Dist: pandas >=0.23
Requires-Dist: seaborn >=0.11.1
Requires-Dist: tables >=3.5
Requires-Dist: lmfit >=1.0.1
Requires-Dist: phconvert >=0.8
Requires-Dist: importlib-metadata ; python_version <= "3.9"
Provides-Extra: gui
Requires-Dist: matplotlib >=3.0.1 ; extra == 'gui'
Requires-Dist: PyQt5 ; extra == 'gui'
Provides-Extra: scientific
Requires-Dist: jupyter ; extra == 'scientific'
Requires-Dist: matplotlib >=3.0.1 ; extra == 'scientific'
